{
    "BTCUSDC": {
        "2h": {
            "sell": {
                "rsi": "2025-06-17T01:00:40.863039+03:00",
                "market_state": "unknown",
                "started_on": "2025-06-16T22:00:00",
                "momentum_strength": "none",
                "log": "2025-06-16T23:16:18.549179+03:00",
                "status": "complete",
                "previous_market_state": "bull"
            },
            "buy": {
                "rsi": "2025-06-17T20:06:33.030622+03:00",
                "market_state": "unknown",
                "started_on": "2025-06-17T17:00:00",
                "momentum_strength": "none",
                "previous_market_state": "neutral_sideways"
            }
        },
        "1h": {
            "sell": {
                "rsi": "2025-06-17T01:04:42.446914+03:00",
                "market_state": "unknown",
                "started_on": "2025-06-16T22:00:00",
                "momentum_strength": "none",
                "previous_market_state": "bull",
                "log": "2025-06-16T23:21:48.069448+03:00",
                "status": "complete"
            },
            "buy": {
                "rsi": "2025-06-17T20:11:58.669327+03:00",
                "market_state": "unknown",
                "started_on": "2025-06-17T17:00:00",
                "momentum_strength": "weak",
                "previous_market_state": "neutral_sideways",
                "log": "2025-06-17T17:12:55.780005+03:00",
                "status": "complete"
            }
        },
        "30m": {
            "sell": {
                "rsi": "2025-06-17T01:06:12.028319+03:00",
                "market_state": "unknown",
                "started_on": "2025-06-16T22:00:00",
                "momentum_strength": "none",
                "previous_market_state": "unknown",
                "log": "2025-06-16T23:53:05.179212+03:00",
                "status": "complete"
            },
            "buy": {
                "rsi": "2025-06-17T20:17:24.407308+03:00",
                "market_state": "unknown",
                "started_on": "2025-06-17T17:00:00",
                "momentum_strength": "weak",
                "previous_market_state": "neutral_sideways",
                "log": "2025-06-17T15:08:48.986493+03:00",
                "status": "complete"
            }
        },
        "15m": {
            "sell": {
                "rsi": "2025-06-16T23:14:38.700397+03:00",
                "market_state": "unknown",
                "started_on": "2025-06-16T22:00:00",
                "momentum_strength": "strong",
                "previous_market_state": "bull",
                "log": "2025-06-17T01:26:45.654524+03:00",
                "status": "complete"
            },
            "buy": {
                "rsi": "2025-06-17T19:50:15.822736+03:00",
                "market_state": "bear",
                "started_on": "2025-06-17T14:00:00",
                "momentum_strength": "none",
                "previous_market_state": "neutral_sideways",
                "log": "2025-06-17T03:27:44.957947+03:00",
                "status": "complete"
            }
        },
        "5m": {
            "buy": {
                "rsi": "2025-06-17T18:23:09.171428+03:00",
                "market_state": "unknown",
                "started_on": "2025-06-17T15:00:00",
                "momentum_strength": "none",
                "previous_market_state": "neutral_sideways",
                "log": "2025-06-17T05:44:27.881877+03:00",
                "status": "complete"
            }
        },
        "3m": {
            "buy": {
                "rsi": "2025-06-17T19:55:41.864337+03:00",
                "market_state": "bear",
                "started_on": "2025-06-17T14:00:00",
                "momentum_strength": "none",
                "previous_market_state": "neutral_sideways",
                "log": "2025-06-17T07:00:57.896798+03:00",
                "status": "complete"
            }
        },
        "1m": {
            "sell": {
                "rsi": "2025-06-17T05:55:30.210406+03:00",
                "market_state": "neutral_sideways",
                "started_on": "2025-06-17T04:00:00",
                "momentum_strength": "strong",
                "previous_market_state": "unknown",
                "log": "2025-06-17T08:17:24.630633+03:00",
                "status": "complete"
            }
        }
    },
    "ETHUSDC": {
        "1h": {
            "sell": {
                "rsi": "2025-06-17T00:00:18.555280+03:00",
                "market_state": "unknown",
                "started_on": "2025-06-16T21:00:00",
                "momentum_strength": "weak",
                "log": "2025-06-16T23:16:23.985040+03:00",
                "status": "complete",
                "previous_market_state": "bull"
            },
            "buy": {
                "rsi": "2025-06-17T19:28:32.057240+03:00",
                "market_state": "unknown",
                "started_on": "2025-06-17T16:00:00",
                "momentum_strength": "none",
                "previous_market_state": "neutral_sideways"
            }
        },
        "30m": {
            "sell": {
                "rsi": "2025-06-16T23:43:47.198097+03:00",
                "market_state": "neutral_sideways",
                "started_on": "2025-06-16T21:00:00",
                "momentum_strength": "strong",
                "log": "2025-06-17T00:37:13.981803+03:00",
                "status": "complete",
                "previous_market_state": "unknown"
            },
            "buy": {
                "rsi": "2025-06-17T20:22:58.232495+03:00",
                "market_state": "unknown",
                "started_on": "2025-06-17T17:00:00",
                "momentum_strength": "weak",
                "previous_market_state": "neutral_sideways",
                "log": "2025-06-17T03:22:19.937615+03:00",
                "status": "complete"
            }
        },
        "2h": {
            "sell": {
                "rsi": "2025-06-16T23:54:49.733397+03:00",
                "market_state": "unknown",
                "started_on": "2025-06-16T21:00:00",
                "momentum_strength": "strong",
                "previous_market_state": "unknown",
                "log": "2025-06-17T00:09:41.134367+03:00",
                "status": "complete"
            }
        },
        "3m": {
            "buy": {
                "rsi": "2025-06-17T18:34:07.404233+03:00",
                "market_state": "bear",
                "started_on": "2025-06-17T13:00:00",
                "momentum_strength": "weak",
                "previous_market_state": "neutral_sideways",
                "log": "2025-06-17T09:11:43.203132+03:00",
                "status": "complete"
            },
            "sell": {
                "rsi": "2025-06-17T05:55:36.150178+03:00",
                "market_state": "neutral_sideways",
                "started_on": "2025-06-17T03:00:00",
                "momentum_strength": "strong",
                "previous_market_state": "unknown",
                "log": "2025-06-17T06:59:25.836032+03:00",
                "status": "complete"
            }
        },
        "5m": {
            "buy": {
                "rsi": "2025-06-17T20:06:37.231580+03:00",
                "market_state": "unknown",
                "started_on": "2025-06-17T17:00:00",
                "momentum_strength": "none",
                "previous_market_state": "neutral_sideways",
                "log": "2025-06-17T06:01:01.987888+03:00",
                "status": "complete"
            }
        },
        "15m": {
            "buy": {
                "rsi": "2025-06-17T19:33:56.257895+03:00",
                "market_state": "bear",
                "started_on": "2025-06-17T13:00:00",
                "momentum_strength": "none",
                "previous_market_state": "neutral_sideways",
                "log": "2025-06-17T05:44:35.344072+03:00",
                "status": "complete"
            }
        },
        "1m": {
            "sell": {
                "rsi": "2025-06-17T15:41:16.021189+03:00",
                "market_state": "neutral_sideways",
                "started_on": "2025-06-17T03:00:00",
                "momentum_strength": "none",
                "previous_market_state": "unknown",
                "log": "2025-06-17T09:49:32.949040+03:00",
                "status": "complete"
            },
            "buy": {
                "rsi": "2025-06-17T18:01:31.134155+03:00",
                "market_state": "neutral_sideways",
                "started_on": "2025-06-17T15:00:00",
                "momentum_strength": "none",
                "previous_market_state": "unknown",
                "log": "2025-06-17T09:54:58.480625+03:00",
                "status": "complete"
            }
        }
    },
    "XRPUSDC": {
        "4h": {
            "sell": {
                "rsi": "2025-06-17T00:00:27.469955+03:00",
                "market_state": "unknown",
                "started_on": "2025-06-16T21:00:00",
                "momentum_strength": "none",
                "log": "2025-06-16T23:14:54.364854+03:00",
                "status": "complete"
            }
        },
        "2h": {
            "sell": {
                "rsi": "2025-06-17T01:04:56.455999+03:00",
                "market_state": "unknown",
                "started_on": "2025-06-16T22:00:00",
                "momentum_strength": "none",
                "previous_market_state": "bull",
                "log": "2025-06-16T23:25:56.298192+03:00",
                "status": "complete"
            }
        },
        "1h": {
            "sell": {
                "rsi": "2025-06-17T01:10:28.762811+03:00",
                "market_state": "unknown",
                "started_on": "2025-06-16T22:00:00",
                "momentum_strength": "none",
                "previous_market_state": "bull",
                "log": "2025-06-16T23:27:32.030230+03:00",
                "status": "complete"
            },
            "buy": {
                "rsi": "2025-06-17T19:55:54.564171+03:00",
                "market_state": "unknown",
                "started_on": "2025-06-16T23:00:00",
                "momentum_strength": "none"
            }
        },
        "30m": {
            "sell": {
                "rsi": "2025-06-17T00:09:50.759910+03:00",
                "market_state": "unknown",
                "started_on": "2025-06-16T21:00:00",
                "momentum_strength": "none",
                "status": "complete",
                "previous_market_state": "bull"
            },
            "buy": {
                "rsi": "2025-06-17T19:50:29.222531+03:00",
                "market_state": "unknown",
                "started_on": "2025-06-16T23:00:00",
                "momentum_strength": "none",
                "log": "2025-06-17T15:19:51.620739+03:00",
                "status": "complete"
            }
        },
        "1m": {
            "buy": {
                "rsi": "2025-06-17T18:01:39.940868+03:00",
                "market_state": "unknown",
                "started_on": "2025-06-16T23:00:00",
                "momentum_strength": "none",
                "log": "2025-06-17T13:31:36.022720+03:00",
                "status": "complete"
            },
            "sell": {
                "rsi": "2025-06-17T15:41:23.614420+03:00",
                "market_state": "unknown",
                "started_on": "2025-06-16T23:00:00",
                "momentum_strength": "strong",
                "log": "2025-06-17T16:02:58.669490+03:00",
                "status": "complete"
            }
        },
        "3m": {
            "buy": {
                "rsi": "2025-06-17T20:06:45.100719+03:00",
                "market_state": "unknown",
                "started_on": "2025-06-16T23:00:00",
                "momentum_strength": "none",
                "log": "2025-06-17T13:26:05.272183+03:00",
                "status": "complete"
            },
            "sell": {
                "rsi": "2025-06-17T16:40:46.549102+03:00",
                "market_state": "unknown",
                "started_on": "2025-06-16T23:00:00",
                "momentum_strength": "strong",
                "log": "2025-06-17T16:46:09.816153+03:00",
                "status": "complete"
            }
        },
        "5m": {
            "buy": {
                "rsi": "2025-06-17T13:20:35.951061+03:00",
                "market_state": "unknown",
                "started_on": "2025-06-16T23:00:00",
                "momentum_strength": "none",
                "log": "2025-06-17T12:15:36.732412+03:00",
                "status": "complete"
            }
        },
        "15m": {
            "buy": {
                "rsi": "2025-06-17T20:01:19.786119+03:00",
                "market_state": "unknown",
                "started_on": "2025-06-16T23:00:00",
                "momentum_strength": "none",
                "log": "2025-06-17T12:10:09.256152+03:00",
                "status": "complete"
            }
        }
    },
    "HBARUSDC": {
        "1m": {
            "buy": {
                "rsi": "2025-06-17T14:14:58.645672+03:00",
                "market_state": "unknown",
                "started_on": "2025-06-16T22:00:00",
                "momentum_strength": "weak",
                "log": "2025-06-17T08:23:15.659999+03:00",
                "status": "complete"
            },
            "sell": {
                "rsi": "2025-06-17T05:55:52.022626+03:00",
                "market_state": "unknown",
                "started_on": "2025-06-16T22:00:00",
                "momentum_strength": "strong",
                "log": "2025-06-17T07:37:50.985280+03:00",
                "status": "complete"
            }
        },
        "5m": {
            "buy": {
                "rsi": "2025-06-17T18:23:30.571733+03:00",
                "market_state": "unknown",
                "started_on": "2025-06-16T22:00:00",
                "momentum_strength": "weak",
                "log": "2025-06-17T04:50:12.559916+03:00",
                "status": "complete"
            }
        },
        "15m": {
            "buy": {
                "rsi": "2025-06-17T19:34:13.873675+03:00",
                "market_state": "unknown",
                "started_on": "2025-06-17T16:00:00",
                "momentum_strength": "weak",
                "log": "2025-06-17T02:06:00.463642+03:00",
                "status": "complete",
                "previous_market_state": "bear"
            }
        },
        "3m": {
            "buy": {
                "rsi": "2025-06-17T18:28:57.435804+03:00",
                "market_state": "bear",
                "started_on": "2025-06-17T15:00:00",
                "momentum_strength": "none",
                "log": "2025-06-17T04:55:43.313371+03:00",
                "status": "complete",
                "previous_market_state": "unknown"
            },
            "sell": {
                "rsi": "2025-06-17T05:59:42.527065+03:00",
                "market_state": "unknown",
                "started_on": "2025-06-16T22:00:00",
                "momentum_strength": "strong",
                "log": "2025-06-17T07:34:10.413335+03:00",
                "status": "complete"
            }
        },
        "30m": {
            "buy": {
                "rsi": "2025-06-17T20:23:16.664584+03:00",
                "market_state": "unknown",
                "started_on": "2025-06-17T17:00:00",
                "momentum_strength": "strong",
                "log": "2025-06-17T03:33:46.228914+03:00",
                "status": "complete",
                "previous_market_state": "bear"
            }
        },
        "1h": {
            "buy": {
                "rsi": "2025-06-17T20:12:19.967967+03:00",
                "market_state": "unknown",
                "started_on": "2025-06-17T17:00:00",
                "momentum_strength": "none",
                "log": "2025-06-17T03:28:13.937264+03:00",
                "status": "complete",
                "previous_market_state": "bear"
            }
        },
        "2h": {
            "buy": {
                "rsi": "2025-06-17T20:17:48.777882+03:00",
                "market_state": "unknown",
                "started_on": "2025-06-17T17:00:00",
                "momentum_strength": "strong",
                "previous_market_state": "bear",
                "log": "2025-06-17T20:28:48.342623+03:00",
                "status": "complete"
            }
        }
    },
    "SOLUSDC": {
        "3m": {
            "buy": {
                "rsi": "2025-06-17T18:23:18.081766+03:00",
                "market_state": "bear",
                "started_on": "2025-06-17T14:00:00",
                "momentum_strength": "weak",
                "log": "2025-06-17T13:58:32.927840+03:00",
                "status": "complete",
                "previous_market_state": "unknown"
            },
            "sell": {
                "rsi": "2025-06-17T05:55:40.246503+03:00",
                "market_state": "unknown",
                "started_on": "2025-06-16T22:00:00",
                "momentum_strength": "strong",
                "log": "2025-06-17T14:41:54.423946+03:00",
                "status": "complete"
            }
        },
        "15m": {
            "buy": {
                "rsi": "2025-06-17T19:50:24.731651+03:00",
                "market_state": "bear",
                "started_on": "2025-06-17T14:00:00",
                "momentum_strength": "none",
                "log": "2025-06-17T13:25:55.952427+03:00",
                "status": "complete",
                "previous_market_state": "unknown"
            }
        },
        "5m": {
            "buy": {
                "rsi": "2025-06-17T18:34:11.499885+03:00",
                "market_state": "bear",
                "started_on": "2025-06-17T14:00:00",
                "momentum_strength": "weak",
                "log": "2025-06-17T13:31:29.265474+03:00",
                "status": "complete",
                "previous_market_state": "unknown"
            }
        },
        "30m": {
            "buy": {
                "rsi": "2025-06-17T20:17:32.697985+03:00",
                "market_state": "unknown",
                "started_on": "2025-06-17T17:00:00",
                "momentum_strength": "weak",
                "log": "2025-06-17T12:04:38.697851+03:00",
                "status": "complete",
                "previous_market_state": "bear"
            }
        },
        "1m": {
            "sell": {
                "rsi": "2025-06-17T05:54:05.116033+03:00",
                "market_state": "unknown",
                "started_on": "2025-06-16T22:00:00",
                "momentum_strength": "strong",
                "log": "2025-06-17T14:44:16.154922+03:00",
                "status": "complete"
            },
            "buy": {
                "rsi": "2025-06-17T16:02:52.626506+03:00",
                "market_state": "unknown",
                "started_on": "2025-06-16T22:00:00",
                "momentum_strength": "strong",
                "log": "2025-06-17T16:24:30.665312+03:00",
                "status": "complete"
            }
        },
        "1h": {
            "buy": {
                "rsi": "2025-06-17T20:12:07.165911+03:00",
                "market_state": "unknown",
                "started_on": "2025-06-17T17:00:00",
                "momentum_strength": "weak",
                "previous_market_state": "bear",
                "log": "2025-06-17T19:39:28.548957+03:00",
                "status": "complete"
            }
        }
    },
    "ADAUSDC": {
        "3m": {
            "buy": {
                "rsi": "2025-06-17T19:55:58.658351+03:00",
                "market_state": "bear",
                "started_on": "2025-06-17T15:00:00",
                "momentum_strength": "none",
                "previous_market_state": "unknown",
                "log": "2025-06-17T06:01:18.678715+03:00",
                "status": "complete"
            },
            "sell": {
                "rsi": "2025-06-17T06:10:36.253895+03:00",
                "market_state": "neutral_sideways",
                "started_on": "2025-06-16T21:00:00",
                "momentum_strength": "strong",
                "log": "2025-06-17T06:48:41.023424+03:00",
                "status": "complete"
            }
        },
        "5m": {
            "buy": {
                "rsi": "2025-06-17T20:01:24.395331+03:00",
                "market_state": "unknown",
                "started_on": "2025-06-17T17:00:00",
                "momentum_strength": "none",
                "log": "2025-06-17T02:05:50.942414+03:00",
                "status": "complete",
                "previous_market_state": "bear"
            }
        },
        "1m": {
            "buy": {
                "rsi": "2025-06-17T18:01:45.061354+03:00",
                "market_state": "unknown",
                "started_on": "2025-06-17T11:00:00",
                "momentum_strength": "none",
                "log": "2025-06-17T07:55:54.075032+03:00",
                "status": "complete",
                "previous_market_state": "neutral_sideways"
            },
            "sell": {
                "rsi": "2025-06-17T05:55:47.923600+03:00",
                "market_state": "neutral_sideways",
                "started_on": "2025-06-16T21:00:00",
                "momentum_strength": "strong",
                "previous_market_state": "unknown",
                "log": "2025-06-17T06:55:47.827232+03:00",
                "status": "complete"
            }
        },
        "30m": {
            "buy": {
                "rsi": "2025-06-17T20:28:40.876055+03:00",
                "market_state": "bear",
                "started_on": "2025-06-17T15:00:00",
                "momentum_strength": "strong",
                "log": "2025-06-17T03:28:05.538476+03:00",
                "status": "complete",
                "previous_market_state": "neutral_sideways"
            }
        },
        "15m": {
            "buy": {
                "rsi": "2025-06-17T19:50:33.640385+03:00",
                "market_state": "bear",
                "started_on": "2025-06-17T15:00:00",
                "momentum_strength": "none",
                "log": "2025-06-17T05:44:49.693432+03:00",
                "status": "complete",
                "previous_market_state": "unknown"
            }
        },
        "1h": {
            "buy": {
                "rsi": "2025-06-17T20:23:10.316433+03:00",
                "market_state": "bear",
                "started_on": "2025-06-17T15:00:00",
                "momentum_strength": "strong",
                "previous_market_state": "unknown",
                "status": "complete"
            }
        },
        "2h": {
            "buy": {
                "rsi": "2025-06-17T20:34:15.309795+03:00",
                "market_state": "bear",
                "started_on": "2025-06-17T15:00:00",
                "momentum_strength": "weak",
                "previous_market_state": "neutral_sideways"
            }
        }
    }
}